push/cmd.py
push/main.py
regmodel-0.2.dist-info/METADATA
regmodel-0.2.dist-info/WHEEL
regmodel-0.2.dist-info/entry_points.txt
regmodel-0.2.dist-info/top_level.txt
regmodel-0.2.dist-info/RECORD
